pypiycj/__init__.py
pypiycj/abc.py
pypiycj-0.0.0.dist-info/METADATA
pypiycj-0.0.0.dist-info/WHEEL
pypiycj-0.0.0.dist-info/RECORD
