Metadata-Version: 2.1
Name: pypiycj
Version: 0.0.0
Summary: ycj package
Author: ycj
Author-email: yanchangjian2019@126.com
Requires-Python: >=3.9,<4.0
Classifier: Programming Language :: Python :: 3
Classifier: Programming Language :: Python :: 3.9
Classifier: Programming Language :: Python :: 3.10
Classifier: Programming Language :: Python :: 3.11
Classifier: Programming Language :: Python :: 3.12
